{
  "era": "meiji",
  "metadata": {
    "totalQuestions": 30,
    "difficulty": {
      "easy": 18,
      "medium": 9,
      "hard": 3
    },
    "lastUpdated": "2025-07-27"
  },
  "questions": [
    {
      "id": "meiji_001",
      "question": "明治維新が始まった年はいつか。",
      "choices": [
        "1868年",
        "1867年",
        "1869年",
        "1870年"
      ],
      "correctAnswer": 0,
      "answer": "1868年",
      "explanation": "1868年に王政復古が行われ、明治新政府が発足して明治維新が始まりました。",
      "difficulty": 1,
      "category": "年代",
      "tags": ["明治維新", "1868年", "基本"]
    },
    {
      "id": "meiji_002",
      "question": "明治政府が掲げたスローガンは何か。",
      "choices": [
        "富国強兵",
        "殖産興業",
        "文明開化",
        "廃藩置県"
      ],
      "correctAnswer": 0,
      "answer": "富国強兵",
      "explanation": "明治政府は国を豊かにし軍事力を強化する「富国強兵」を基本政策としました。",
      "difficulty": 1,
      "category": "政策",
      "tags": ["富国強兵", "基本政策", "基本"]
    },
    {
      "id": "meiji_003",
      "question": "廃藩置県が行われた年はいつか。",
      "answer": "1871年",
      "explanation": "1871年に廃藩置県が実施され、藩が廃止されて県が設置されました。",
      "difficulty": 1,
      "category": "政治改革",
      "tags": ["廃藩置県", "1871年", "中央集権"]
    },
    {
      "id": "meiji_004",
      "question": "四民平等を実現した政策は何か。",
      "choices": [
        "身分制度の廃止",
        "地租改正",
        "学制発布",
        "徴兵令"
      ],
      "correctAnswer": 0,
      "answer": "身分制度の廃止",
      "explanation": "明治政府は士農工商の身分制度を廃止し、四民平等を実現しました。",
      "difficulty": 1,
      "category": "社会改革",
      "tags": ["四民平等", "身分制廃止", "基本"]
    },
    {
      "id": "meiji_005",
      "question": "地租改正が行われた目的は何か。",
      "answer": "安定した税収の確保",
      "explanation": "地租改正により土地の価格に基づく金納制が導入され、政府の安定した税収が確保されました。",
      "difficulty": 2,
      "category": "経済改革",
      "tags": ["地租改正", "金納制", "税制改革"]
    },
    {
      "id": "meiji_006",
      "question": "学制が発布された年はいつか。",
      "choices": [
        "1872年",
        "1871年",
        "1873年",
        "1874年"
      ],
      "correctAnswer": 0,
      "answer": "1872年",
      "explanation": "1872年に学制が発布され、近代的な教育制度の基礎が築かれました。",
      "difficulty": 1,
      "category": "教育",
      "tags": ["学制", "1872年", "教育制度"]
    },
    {
      "id": "meiji_007",
      "question": "徴兵令が発布された年はいつか。",
      "answer": "1873年",
      "explanation": "1873年に徴兵令が発布され、国民皆兵制度が導入されました。",
      "difficulty": 1,
      "category": "軍事",
      "tags": ["徴兵令", "1873年", "国民皆兵"]
    },
    {
      "id": "meiji_008",
      "question": "岩倉使節団の目的は何か。",
      "choices": [
        "不平等条約の改正交渉",
        "西洋文明の視察",
        "貿易協定の締結",
        "軍事同盟の締結"
      ],
      "correctAnswer": 0,
      "answer": "不平等条約の改正交渉",
      "explanation": "岩倉使節団は不平等条約の改正交渉と西洋文明の視察を目的として派遣されました。",
      "difficulty": 2,
      "category": "外交",
      "tags": ["岩倉使節団", "条約改正", "西洋視察"]
    },
    {
      "id": "meiji_009",
      "question": "西南戦争が起こった年はいつか。",
      "choices": [
        "1877年",
        "1876年",
        "1878年",
        "1879年"
      ],
      "correctAnswer": 0,
      "answer": "1877年",
      "explanation": "1877年に西郷隆盛を中心とする士族の反乱である西南戦争が起こりました。",
      "difficulty": 1,
      "category": "戦争",
      "tags": ["西南戦争", "1877年", "西郷隆盛"]
    },
    {
      "id": "meiji_010",
      "question": "大日本帝国憲法が発布された年はいつか。",
      "answer": "1889年",
      "explanation": "1889年に大日本帝国憲法が発布され、近代的な立憲政治が始まりました。",
      "difficulty": 1,
      "category": "政治",
      "tags": ["大日本帝国憲法", "1889年", "立憲政治"]
    },
    {
      "id": "meiji_011",
      "question": "初代内閣総理大臣は誰か。",
      "choices": [
        "伊藤博文",
        "黒田清隆",
        "山縣有朋",
        "松方正義"
      ],
      "correctAnswer": 0,
      "answer": "伊藤博文",
      "explanation": "1885年に内閣制度が発足し、伊藤博文が初代内閣総理大臣に就任しました。",
      "difficulty": 1,
      "category": "政治",
      "tags": ["伊藤博文", "初代総理", "内閣制度"]
    },
    {
      "id": "meiji_012",
      "question": "帝国議会が開設された年はいつか。",
      "choices": [
        "1890年",
        "1889年",
        "1891年",
        "1888年"
      ],
      "correctAnswer": 0,
      "answer": "1890年",
      "explanation": "1890年に帝国議会が開設され、衆議院と貴族院による二院制が始まりました。",
      "difficulty": 1,
      "category": "政治",
      "tags": ["帝国議会", "1890年", "二院制"]
    },
    {
      "id": "meiji_013",
      "question": "日清戦争が行われた年はいつか。",
      "answer": "1894-1895年",
      "explanation": "1894年から1895年にかけて日清戦争が行われ、日本が勝利しました。",
      "difficulty": 1,
      "category": "戦争",
      "tags": ["日清戦争", "1894-1895年", "基本"]
    },
    {
      "id": "meiji_014",
      "question": "日清戦争後に結ばれた条約は何か。",
      "choices": [
        "下関条約",
        "日韓協約",
        "ポーツマス条約",
        "日英同盟"
      ],
      "correctAnswer": 0,
      "answer": "下関条約",
      "explanation": "1895年に下関条約が結ばれ、遼東半島・台湾・澎湖諸島を日本が獲得しました。",
      "difficulty": 1,
      "category": "条約",
      "tags": ["下関条約", "1895年", "台湾獲得"]
    },
    {
      "id": "meiji_015",
      "question": "三国干渉を行った国はどこか。",
      "answer": "ロシア・ドイツ・フランス",
      "explanation": "下関条約後、ロシア・ドイツ・フランスが三国干渉を行い、日本は遼東半島を清に返還しました。",
      "difficulty": 2,
      "category": "外交",
      "tags": ["三国干渉", "遼東半島返還", "外交圧力"]
    },
    {
      "id": "meiji_016",
      "question": "日露戦争が行われた年はいつか。",
      "choices": [
        "1904-1905年",
        "1903-1904年",
        "1905-1906年",
        "1902-1903年"
      ],
      "correctAnswer": 0,
      "answer": "1904-1905年",
      "explanation": "1904年から1905年にかけて日露戦争が行われ、日本が勝利しました。",
      "difficulty": 1,
      "category": "戦争",
      "tags": ["日露戦争", "1904-1905年", "基本"]
    },
    {
      "id": "meiji_017",
      "question": "日露戦争の講和条約は何か。",
      "answer": "ポーツマス条約",
      "explanation": "1905年にポーツマス条約が結ばれ、日本は南満州の権益と南樺太を獲得しました。",
      "difficulty": 1,
      "category": "条約",
      "tags": ["ポーツマス条約", "1905年", "南満州"]
    },
    {
      "id": "meiji_018",
      "question": "韓国併合が行われた年はいつか。",
      "choices": [
        "1910年",
        "1909年",
        "1911年",
        "1908年"
      ],
      "correctAnswer": 0,
      "answer": "1910年",
      "explanation": "1910年に韓国併合が行われ、朝鮮は日本の植民地となりました。",
      "difficulty": 1,
      "category": "植民地",
      "tags": ["韓国併合", "1910年", "植民地化"]
    },
    {
      "id": "meiji_019",
      "question": "明治時代の産業革命で中心となった産業は何か。",
      "answer": "製糸業",
      "explanation": "明治時代の産業革命では製糸業が中心となり、生糸が主要な輸出品でした。",
      "difficulty": 1,
      "category": "経済",
      "tags": ["製糸業", "産業革命", "生糸輸出"]
    },
    {
      "id": "meiji_020",
      "question": "八幡製鉄所が設立された目的は何か。",
      "choices": [
        "重工業の発達",
        "軽工業の発達",
        "農業の機械化",
        "交通の発達"
      ],
      "correctAnswer": 0,
      "answer": "重工業の発達",
      "explanation": "1901年に設立された八幡製鉄所は日本の重工業発達の象徴でした。",
      "difficulty": 2,
      "category": "工業",
      "tags": ["八幡製鉄所", "重工業", "1901年"]
    },
    {
      "id": "meiji_021",
      "question": "新橋・横浜間に鉄道が開通した年はいつか。",
      "answer": "1872年",
      "explanation": "1872年に新橋・横浜間に日本初の鉄道が開通し、近代交通の始まりとなりました。",
      "difficulty": 2,
      "category": "交通",
      "tags": ["鉄道開通", "1872年", "新橋横浜"]
    },
    {
      "id": "meiji_022",
      "question": "明治時代の文化運動として有名なものは何か。",
      "choices": [
        "文明開化",
        "国粋主義",
        "民権運動",
        "社会主義"
      ],
      "correctAnswer": 0,
      "answer": "文明開化",
      "explanation": "明治時代初期には西洋文明を積極的に取り入れる文明開化が進みました。",
      "difficulty": 1,
      "category": "文化",
      "tags": ["文明開化", "西洋文明", "基本"]
    },
    {
      "id": "meiji_023",
      "question": "自由民権運動の指導者は誰か。",
      "answer": "板垣退助",
      "explanation": "板垣退助は自由民権運動の指導者として「自由党」を結成し、国会開設を要求しました。",
      "difficulty": 1,
      "category": "政治運動",
      "tags": ["板垣退助", "自由民権運動", "自由党"]
    },
    {
      "id": "meiji_024",
      "question": "明治時代の教育勅語が発布された年はいつか。",
      "choices": [
        "1890年",
        "1889年",
        "1891年",
        "1892年"
      ],
      "correctAnswer": 0,
      "answer": "1890年",
      "explanation": "1890年に教育勅語が発布され、天皇制国家の道徳教育の基準となりました。",
      "difficulty": 2,
      "category": "教育",
      "tags": ["教育勅語", "1890年", "道徳教育"]
    },
    {
      "id": "meiji_025",
      "question": "明治時代の文学で代表的な作家は誰か。",
      "answer": "夏目漱石",
      "explanation": "夏目漱石は明治時代の代表的な文学者で、「吾輩は猫である」「坊っちゃん」などを著しました。",
      "difficulty": 1,
      "category": "文学",
      "tags": ["夏目漱石", "明治文学", "吾輩は猫である"]
    },
    {
      "id": "meiji_026",
      "question": "明治時代の美術で西洋画を取り入れた画家は誰か。",
      "choices": [
        "高橋由一",
        "狩野芳崖",
        "横山大観",
        "菱田春草"
      ],
      "correctAnswer": 0,
      "answer": "高橋由一",
      "explanation": "高橋由一は日本近代洋画の父と呼ばれ、西洋の油彩画技法を日本に導入しました。",
      "difficulty": 2,
      "category": "美術",
      "tags": ["高橋由一", "洋画", "油彩画"]
    },
    {
      "id": "meiji_027",
      "question": "明治時代の宗教政策として行われたものは何か。",
      "answer": "神仏分離",
      "explanation": "明治政府は神仏分離令により、それまで混合していた神道と仏教を分離しました。",
      "difficulty": 2,
      "category": "宗教政策",
      "tags": ["神仏分離", "宗教政策", "神道"]
    },
    {
      "id": "meiji_028",
      "question": "明治時代の女性教育で設立された学校は何か。",
      "choices": [
        "津田塾",
        "慶應義塾",
        "早稲田大学",
        "明治大学"
      ],
      "correctAnswer": 0,
      "answer": "津田塾",
      "explanation": "津田梅子により設立された津田塾は、明治時代の女性高等教育の先駆けとなりました。",
      "difficulty": 3,
      "category": "女性教育",
      "tags": ["津田梅子", "津田塾", "女性教育"]
    },
    {
      "id": "meiji_029",
      "question": "明治時代の労働運動で重要な出来事は何か。",
      "answer": "足尾銅山鉱毒事件",
      "explanation": "足尾銅山の鉱毒事件は明治時代の公害問題の先駆けで、田中正造が告発しました。",
      "difficulty": 3,
      "category": "社会問題",
      "tags": ["足尾銅山", "鉱毒事件", "田中正造"]
    },
    {
      "id": "meiji_030",
      "question": "明治天皇が崩御した年はいつか。",
      "choices": [
        "1912年",
        "1911年",
        "1913年",
        "1910年"
      ],
      "correctAnswer": 0,
      "answer": "1912年",
      "explanation": "1912年に明治天皇が崩御し、大正時代が始まりました。",
      "difficulty": 2,
      "category": "年代",
      "tags": ["明治天皇崩御", "1912年", "大正時代開始"]
    }
  ]
}